cat/__init__.py
cat/cat.py
cat/catffi.py
cat/const.py
cat/container.py
cat/event.py
cat/heartbeat.py
cat/message.py
cat/metric.py
cat/sdk.py
cat/transaction.py
cat/utils.py
cat/version.py
cat/lib/darwin/libcatclient.dylib
cat/lib/linux-glibc/libcatclient.so
cat/lib/linux-musl-libc/libcatclient.so
huifu_cat_sdk-1.0.3.dist-info/METADATA
huifu_cat_sdk-1.0.3.dist-info/WHEEL
huifu_cat_sdk-1.0.3.dist-info/top_level.txt
huifu_cat_sdk-1.0.3.dist-info/RECORD
